visualizer/__init__.py
visualizer/cli.py
visualizer/exporter.py
visualizer/graphical_renderer.py
visualizer/tree_builder.py
visualizer/export/__init__.py
visualizer/export/ascii_exporter.py
visualizer/export/matplotlib_exporter.py
visualizer/export/networkx_exporter.py
dirstructviz-3.2.0.dist-info/LICENSE
dirstructviz-3.2.0.dist-info/METADATA
dirstructviz-3.2.0.dist-info/WHEEL
dirstructviz-3.2.0.dist-info/entry_points.txt
dirstructviz-3.2.0.dist-info/top_level.txt
dirstructviz-3.2.0.dist-info/RECORD
