Metadata-Version: 2.1
Name: dirstructviz
Version: 3.2.0
Summary: A versatile directory structure visualizer and exporter utility for Python projects.
Author: Abhinav Hudda
Author-email: upstage.barrier_0x@icloud.com
Classifier: Development Status :: 4 - Beta
Classifier: Environment :: Console
Classifier: Intended Audience :: Developers
Classifier: License :: OSI Approved :: MIT License
Classifier: Programming Language :: Python :: 3
Classifier: Programming Language :: Python :: 3.7
Classifier: Programming Language :: Python :: 3.8
Classifier: Programming Language :: Python :: 3.9
Classifier: Programming Language :: Python :: 3.10
Classifier: Operating System :: OS Independent
Classifier: Topic :: Software Development :: Libraries :: Python Modules
Classifier: Topic :: Utilities
Requires-Python: >=3.7
License-File: LICENSE
Requires-Dist: click >=8.0
Requires-Dist: rich
Requires-Dist: matplotlib >=3.5
Requires-Dist: networkx >=2.5
